marathon_chai/__init__.py
marathon_chai/canlib.py
marathon_chai/chai_header.py
marathon_chai-0.2a0.dist-info/METADATA
marathon_chai-0.2a0.dist-info/WHEEL
marathon_chai-0.2a0.dist-info/entry_points.txt
marathon_chai-0.2a0.dist-info/top_level.txt
marathon_chai-0.2a0.dist-info/RECORD
