Metadata-Version: 2.1
Name: marathon_chai
Version: 0.2a0
Summary: Python driver for Marathon CHAI interface
Author: KirichRus
Author-email: kirichrus@gmail.com
Requires-Python: >=3.9
Requires-Dist: python-can
